setup.py
matop2/__init__.py
matop2/matrix_operations.py
matop2.egg-info/PKG-INFO
matop2.egg-info/SOURCES.txt
matop2.egg-info/dependency_links.txt
matop2.egg-info/not-zip-safe
matop2.egg-info/top_level.txt