Metadata-Version: 1.0
Name: matop2
Version: 0.6
Summary: Matrix Operations
Home-page: UNKNOWN
Author: Rajesh Kumar Bandaru
Author-email: rkumar70900@gmail.com
License: UNKNOWN
Platform: UNKNOWN
